
[
  {
    "id": 1721242200000,
    "title": "Rip Current in Santa Monica Beach, CA",
    "user": "Anonymous",
    "timeAgo": "2 months ago",
    "description": "Strong, narrow rip current pulling swimmers away from shore near lifeguard tower 18. Several swimmers struggling to return.",
    "tags": [
      "rip current",
      "high"
    ],
    "verified": true,
    "type": "currents",
    "severity": "high",
    "location": "Santa Monica Beach, CA",
    "date": "2024-09-15T14:30:00.000Z",
    "imageUrl": "https://picsum.photos/seed/1721242200000/400/200",
    "imageHint": "rip current ocean",
    "lat": 34.0195,
    "lng": -118.4912
  },
  {
    "id": 1721242200001,
    "title": "Tsunami Warning in Hilo, HI",
    "user": "Anonymous",
    "timeAgo": "4 months ago",
    "description": "Tsunami alert issued after 7.8 magnitude earthquake off coast. Waves expected to reach 3 meters. Evacuation orders in effect.",
    "tags": [
      "tsunami",
      "extreme"
    ],
    "verified": false,
    "type": "tsunami",
    "severity": "extreme",
    "location": "Hilo, HI",
    "date": "2024-03-22T08:45:00.000Z",
    "imageUrl": "https://picsum.photos/seed/1721242200001/400/200",
    "imageHint": "tsunami warning ocean",
    "lat": 19.7297,
    "lng": -155.09
  },
  {
    "id": 1721242200002,
    "title": "Oil Spill in Galveston Bay, TX",
    "user": "Anonymous",
    "timeAgo": "now",
    "description": "Large oil slick approximately 2 miles long drifting toward shoreline. Strong petroleum odor. Wildlife observed in distress.",
    "tags": [
      "other",
      "high"
    ],
    "verified": true,
    "type": "other",
    "severity": "high",
    "location": "Galveston Bay, TX",
    "date": "2024-11-07T10:15:00.000Z",
    "imageUrl": "https://picsum.photos/seed/1721242200002/400/200",
    "imageHint": "oil spill ocean",
    "lat": 29.513,
    "lng": -94.8996
  },
  {
    "id": 1721242200003,
    "title": "Harmful Algal Bloom in Sanibel Island, FL",
    "user": "Anonymous",
    "timeAgo": "1 day ago",
    "description": "Red tide event causing respiratory irritation in beachgoers. Dead fish washing ashore along 1-mile stretch.",
    "tags": [
      "other",
      "medium"
    ],
    "verified": false,
    "type": "other",
    "severity": "medium",
    "location": "Sanibel Island, FL",
    "date": "2024-07-29T16:20:00.000Z",
    "imageUrl": "https://picsum.photos/seed/1721242200003/400/200",
    "imageHint": "algal bloom ocean",
    "lat": 26.4487,
    "lng": -82.1098
  },
  {
    "id": 1721242200004,
    "title": "Marine Debris in Cannon Beach, OR",
    "user": "Anonymous",
    "timeAgo": "2 months ago",
    "description": "Large fishing net and plastic debris accumulation covering approximately 200 yards of beach. Hazard to wildlife and navigation.",
    "tags": [
      "other",
      "medium"
    ],
    "verified": true,
    "type": "other",
    "severity": "medium",
    "location": "Cannon Beach, OR",
    "date": "2024-05-12T11:00:00.000Z",
    "imageUrl": "https://picsum.photos/seed/1721242200004/400/200",
    "imageHint": "marine debris ocean",
    "lat": 45.8918,
    "lng": -123.9615
  },
  {
    "id": 1721242200005,
    "title": "Sneaker Wave in Pfeiffer Beach, Big Sur, CA",
    "user": "Anonymous",
    "timeAgo": "6 months ago",
    "description": "Unexpected large waves sweeping further up beach than normal. Several people caught off guard, equipment washed away.",
    "tags": [
      "waves",
      "high"
    ],
    "verified": false,
    "type": "waves",
    "severity": "high",
    "location": "Pfeiffer Beach, Big Sur, CA",
    "date": "2024-01-18T13:45:00.000Z",
    "imageUrl": "https://picsum.photos/seed/1721242200005/400/200",
    "imageHint": "sneaker wave ocean",
    "lat": 36.2383,
    "lng": -121.8122
  },
  {
    "id": 1721242200006,
    "title": "Shark Sighting in Outer Banks, NC",
    "user": "Anonymous",
    "timeAgo": "1 month ago",
    "description": "Approximately 10-foot great white shark circling 100 yards from shore. Beach temporarily closed for safety.",
    "tags": [
      "other",
      "medium"
    ],
    "verified": true,
    "type": "other",
    "severity": "medium",
    "location": "Outer Banks, NC",
    "date": "2024-08-22T09:30:00.000Z",
    "imageUrl": "https://picsum.photos/seed/1721242200006/400/200",
    "imageHint": "shark sighting ocean",
    "lat": 35.562,
    "lng": -75.4678
  },
  {
    "id": 1721242200007,
    "title": "Coastal Erosion in Montauk Point, NY",
    "user": "Anonymous",
    "timeAgo": "now",
    "description": "Recent storm caused significant cliff erosion. Unstable cliffs pose danger to hikers and beachgoers below.",
    "tags": [
      "erosion",
      "low"
    ],
    "verified": true,
    "type": "erosion",
    "severity": "low",
    "location": "Montauk Point, NY",
    "date": "2024-12-03T15:00:00.000Z",
    "imageUrl": "https://picsum.photos/seed/1721242200007/400/200",
    "imageHint": "coastal erosion ocean",
    "lat": 41.0729,
    "lng": -71.8572
  },
  {
    "id": 1721242200008,
    "title": "Jellyfish Bloom in Myrtle Beach, SC",
    "user": "Anonymous",
    "timeAgo": "1 month ago",
    "description": "Large concentration of moon jellyfish along shoreline. Multiple stings reported. Swimmers advised to wear protective clothing.",
    "tags": [
      "other",
      "low"
    ],
    "verified": false,
    "type": "other",
    "severity": "low",
    "location": "Myrtle Beach, SC",
    "date": "2024-06-14T14:00:00.000Z",
    "imageUrl": "https://picsum.photos/seed/1721242200008/400/200",
    "imageHint": "jellyfish bloom ocean",
    "lat": 33.6891,
    "lng": -78.8867
  },
  {
    "id": 1721242200009,
    "title": "Chemical Pollution in Newport Beach, CA",
    "user": "Anonymous",
    "timeAgo": "now",
    "description": "Unknown chemical sheen on water surface near harbor entrance. Strong chemical odor causing eye irritation.",
    "tags": [
      "other",
      "high"
    ],
    "verified": true,
    "type": "other",
    "severity": "high",
    "location": "Newport Beach, CA",
    "date": "2024-10-05T07:30:00.000Z",
    "imageUrl": "https://picsum.photos/seed/1721242200009/400/200",
    "imageHint": "chemical pollution ocean",
    "lat": 33.6189,
    "lng": -117.9298
  },
  {
    "id": 1721242200010,
    "title": "Rip Current in Cocoa Beach, FL",
    "user": "Anonymous",
    "timeAgo": "3 months ago",
    "description": "Moderate rip current developing near pier. Swimmers advised to avoid area between flags 12-15.",
    "tags": [
      "rip current",
      "medium"
    ],
    "verified": false,
    "type": "currents",
    "severity": "medium",
    "location": "Cocoa Beach, FL",
    "date": "2024-04-19T16:45:00.000Z",
    "imageUrl": "https://picsum.photos/seed/1721242200010/400/200",
    "imageHint": "rip current ocean",
    "lat": 28.32,
    "lng": -80.6077
  },
  {
    "id": 1721242200011,
    "title": "Tsunami Warning in Crescent City, CA",
    "user": "Anonymous",
    "timeAgo": "5 months ago",
    "description": "Tsunami advisory following undersea landslide. Coastal areas evacuated. Expected wave height 1-2 meters.",
    "tags": [
      "tsunami",
      "extreme"
    ],
    "verified": true,
    "type": "tsunami",
    "severity": "extreme",
    "location": "Crescent City, CA",
    "date": "2024-02-11T23:15:00.000Z",
    "imageUrl": "https://picsum.photos/seed/1721242200011/400/200",
    "imageHint": "tsunami warning ocean",
    "lat": 41.7558,
    "lng": -124.2026
  },
  {
    "id": 1721242200012,
    "title": "Marine Debris in Long Beach, WA",
    "user": "Anonymous",
    "timeAgo": "now",
    "description": "Large shipping container washed ashore with hazardous materials labels visible. Area cordoned off pending inspection.",
    "tags": [
      "other",
      "high"
    ],
    "verified": true,
    "type": "other",
    "severity": "high",
    "location": "Long Beach, WA",
    "date": "2024-09-28T12:30:00.000Z",
    "imageUrl": "https://picsum.photos/seed/1721242200012/400/200",
    "imageHint": "marine debris ocean",
    "lat": 46.3532,
    "lng": -124.0554
  },
  {
    "id": 1721242200013,
    "title": "Harmful Algal Bloom in Cape Cod, MA",
    "user": "Anonymous",
    "timeAgo": "now",
    "description": "Toxic algae bloom causing shellfish harvesting closure. Water discoloration observed along northern beaches.",
    "tags": [
      "other",
      "high"
    ],
    "verified": false,
    "type": "other",
    "severity": "high",
    "location": "Cape Cod, MA",
    "date": "2024-08-07T10:00:00.000Z",
    "imageUrl": "https://picsum.photos/seed/1721242200013/400/200",
    "imageHint": "algal bloom ocean",
    "lat": 41.668,
    "lng": -70.2949
  },
  {
    "id": 1721242200014,
    "title": "Sneaker Wave in Rialto Beach, WA",
    "user": "Anonymous",
    "timeAgo": "now",
    "description": "Unexpected large waves reaching log line. Several campers' gear soaked. Caution advised for beach hikers.",
    "tags": [
      "waves",
      "medium"
    ],
    "verified": true,
    "type": "waves",
    "severity": "medium",
    "location": "Rialto Beach, WA",
    "date": "2024-11-25T14:15:00.000Z",
    "imageUrl": "https://picsum.photos/seed/1721242200014/400/200",
    "imageHint": "sneaker wave ocean",
    "lat": 47.919,
    "lng": -124.641
  },
  {
    "id": 1721242200015,
    "title": "Oil Spill in Huntington Beach, CA",
    "user": "Anonymous",
    "timeAgo": "1 week ago",
    "description": "Small fuel spill from recreational boat. Sheen approximately 100 yards long moving with current.",
    "tags": [
      "other",
      "medium"
    ],
    "verified": false,
    "type": "other",
    "severity": "medium",
    "location": "Huntington Beach, CA",
    "date": "2024-07-03T18:20:00.000Z",
    "imageUrl": "https://picsum.photos/seed/1721242200015/400/200",
    "imageHint": "oil spill ocean",
    "lat": 33.66,
    "lng": -117.9983
  },
  {
    "id": 1721242200016,
    "title": "Shark Sighting in Daytona Beach, FL",
    "user": "Anonymous",
    "timeAgo": "2 months ago",
    "description": "Small shark (estimated 4-5 feet) spotted close to shore. Beach remains open with increased patrols.",
    "tags": [
      "other",
      "low"
    ],
    "verified": true,
    "type": "other",
    "severity": "low",
    "location": "Daytona Beach, FL",
    "date": "2024-05-30T11:45:00.000Z",
    "imageUrl": "https://picsum.photos/seed/1721242200016/400/200",
    "imageHint": "shark sighting ocean",
    "lat": 29.2108,
    "lng": -81.0228
  },
  {
    "id": 1721242200017,
    "title": "Coastal Erosion in Pacific Palisades, CA",
    "user": "Anonymous",
    "timeAgo": "6 months ago",
    "description": "Recent landslides have undermined coastal bluffs. Several homes evacuated. Beach access closed indefinitely.",
    "tags": [
      "erosion",
      "high"
    ],
    "verified": true,
    "type": "erosion",
    "severity": "high",
    "location": "Pacific Palisades, CA",
    "date": "2024-01-05T09:00:00.000Z",
    "imageUrl": "https://picsum.photos/seed/1721242200017/400/200",
    "imageHint": "coastal erosion ocean",
    "lat": 34.044,
    "lng": -118.53
  },
  {
    "id": 1721242200018,
    "title": "Jellyfish Bloom in Gulf Shores, AL",
    "user": "Anonymous",
    "timeAgo": "now",
    "description": "Portuguese man o' war washing ashore. Multiple painful stings reported. Purple flags flying.",
    "tags": [
      "other",
      "medium"
    ],
    "verified": false,
    "type": "other",
    "severity": "medium",
    "location": "Gulf Shores, AL",
    "date": "2024-09-08T13:30:00.000Z",
    "imageUrl": "https://picsum.photos/seed/1721242200018/400/200",
    "imageHint": "jellyfish bloom ocean",
    "lat": 30.246,
    "lng": -87.7008
  },
  {
    "id": 1721242200019,
    "title": "Chemical Pollution in Portland, ME",
    "user": "Anonymous",
    "timeAgo": "4 months ago",
    "description": "Industrial discharge creating toxic foam along waterfront. Strong chemical smell. Area evacuated.",
    "tags": [
      "other",
      "extreme"
    ],
    "verified": true,
    "type": "other",
    "severity": "extreme",
    "location": "Portland, ME",
    "date": "2024-03-14T06:45:00.000Z",
    "imageUrl": "https://picsum.photos/seed/1721242200019/400/200",
    "imageHint": "chemical pollution ocean",
    "lat": 43.6615,
    "lng": -70.2553
  },
  {
    "id": 1721242200020,
    "title": "Rip Current in Virginia Beach, VA",
    "user": "Anonymous",
    "timeAgo": "now",
    "description": "Multiple strong rip currents forming after storm. Lifeguards performing numerous rescues. Swimmers advised to stay close to shore.",
    "tags": [
      "rip current",
      "high"
    ],
    "verified": true,
    "type": "currents",
    "severity": "high",
    "location": "Virginia Beach, VA",
    "date": "2024-08-12T15:30:00.000Z",
    "imageUrl": "https://picsum.photos/seed/1721242200020/400/200",
    "imageHint": "rip current ocean",
    "lat": 36.8529,
    "lng": -75.978
  },
  {
    "id": 1721242200021,
    "title": "Marine Debris in Coronado Beach, CA",
    "user": "Anonymous",
    "timeAgo": "now",
    "description": "Scattered plastic debris and fishing line along high tide line. Cleanup organized for tomorrow.",
    "tags": [
      "other",
      "low"
    ],
    "verified": false,
    "type": "other",
    "severity": "low",
    "location": "Coronado Beach, CA",
    "date": "2024-10-22T14:00:00.000Z",
    "imageUrl": "https://picsum.photos/seed/1721242200021/400/200",
    "imageHint": "marine debris ocean",
    "lat": 32.6842,
    "lng": -117.1831
  },
  {
    "id": 1721242200022,
    "title": "Harmful Algal Bloom in Lake Erie Shoreline, OH",
    "user": "Anonymous",
    "timeAgo": "now",
    "description": "Blue-green algae bloom creating green scum on water surface. Swimming advisory issued.",
    "tags": [
      "other",
      "medium"
    ],
    "verified": true,
    "type": "other",
    "severity": "medium",
    "location": "Lake Erie Shoreline, OH",
    "date": "2024-07-19T12:15:00.000Z",
    "imageUrl": "https://picsum.photos/seed/1721242200022/400/200",
    "imageHint": "algal bloom lake",
    "lat": 41.6852,
    "lng": -83.0526
  },
  {
    "id": 1721242200023,
    "title": "Sneaker Wave in Bandon, OR",
    "user": "Anonymous",
    "timeAgo": "now",
    "description": "Exceptionally large waves surprising tourists on rock formations. Several people required rescue from rising tide.",
    "tags": [
      "waves",
      "high"
    ],
    "verified": true,
    "type": "waves",
    "severity": "high",
    "location": "Bandon, OR",
    "date": "2024-12-29T11:30:00.000Z",
    "imageUrl": "https://picsum.photos/seed/1721242200023/400/200",
    "imageHint": "sneaker wave ocean",
    "lat": 43.1182,
    "lng": -124.4084
  },
  {
    "id": 1721242200024,
    "title": "Oil Spill in Marina del Rey, CA",
    "user": "Anonymous",
    "timeAgo": "3 months ago",
    "description": "Small diesel spill from docked vessel. Containment boom deployed. Minimal environmental impact expected.",
    "tags": [
      "other",
      "low"
    ],
    "verified": false,
    "type": "other",
    "severity": "low",
    "location": "Marina del Rey, CA",
    "date": "2024-04-05T16:00:00.000Z",
    "imageUrl": "https://picsum.photos/seed/1721242200024/400/200",
    "imageHint": "oil spill marina",
    "lat": 33.9803,
    "lng": -118.4517
  }
]

    